marenan-0.0.4.dist-info/METADATA
marenan-0.0.4.dist-info/WHEEL
marenan-0.0.4.dist-info/entry_points.txt
marenan/__init__.py
marenan/__main__.py
marenan/cli/__init__.py
marenan/cli/main.py
marenan/marenanDay.py
marenan-0.0.4.dist-info/RECORD
