Metadata-Version: 2.1
Name: marenan
Version: 0.0.4
Summary: Pacote para simbolizar o amor entre Mari e Renan.
Author-Email: Renan Passos <renanpassos@poli.ufrj.br>
License: MIT
Requires-Python: >=3.8
